MANIFEST.in
README
setup.py
lib/merchant_gateways/__init__.py
lib/merchant_gateways.egg-info/PKG-INFO
lib/merchant_gateways.egg-info/SOURCES.txt
lib/merchant_gateways.egg-info/dependency_links.txt
lib/merchant_gateways.egg-info/requires.txt
lib/merchant_gateways.egg-info/top_level.txt
lib/merchant_gateways/billing/__init__.py
lib/merchant_gateways/billing/avs_result.py
lib/merchant_gateways/billing/common.py
lib/merchant_gateways/billing/credit_card.py
lib/merchant_gateways/billing/cvv_result.py
lib/merchant_gateways/billing/response.py
lib/merchant_gateways/billing/gateways/__init__.py
lib/merchant_gateways/billing/gateways/authorize_net.py
lib/merchant_gateways/billing/gateways/bogus.py
lib/merchant_gateways/billing/gateways/braintree_blue.py
lib/merchant_gateways/billing/gateways/braintree_orange.py
lib/merchant_gateways/billing/gateways/cybersource.py
lib/merchant_gateways/billing/gateways/gateway.py
lib/merchant_gateways/billing/gateways/payflow.py
lib/merchant_gateways/billing/gateways/paymentech_orbital.py
lib/merchant_gateways/lib/__init__.py
lib/merchant_gateways/lib/post.py
lib/merchant_gateways/tests/__init__.py
lib/merchant_gateways/tests/test_helper.py
lib/merchant_gateways/tests/billing/__init__.py
lib/merchant_gateways/tests/billing/gateways/__init__.py
lib/merchant_gateways/tests/billing/gateways/authorize_net_suite.py
lib/merchant_gateways/tests/billing/gateways/braintree_blue_suite.py
lib/merchant_gateways/tests/billing/gateways/braintree_orange_suite.py
lib/merchant_gateways/tests/billing/gateways/cybersource_suite.py
lib/merchant_gateways/tests/billing/gateways/gateway_suite.py
lib/merchant_gateways/tests/billing/gateways/payflow_suite.py
lib/merchant_gateways/tests/billing/gateways/paymentech_orbital_suite.py
lib/merchant_gateways/tests/billing/gateways/schemas/cybersource/CyberSourceTransaction_1.71.xsd
lib/merchant_gateways/tests/billing/gateways/schemas/paymentech_orbital/Request_PTI49.xsd
lib/merchant_gateways/tests/billing/gateways/schemas/paymentech_orbital/Request_PTI50.xsd
lib/merchant_gateways/tests/billing/gateways/schemas/paymentech_orbital/Response_PTI50.xsd
lib/merchant_gateways/tests/billing/gateways/schemas/xmlpay/XMLPay.dtd
