Metadata-Version: 1.0
Name: merchant-gateways
Version: 0.0.1
Summary: Unifying the diversity of gateways into a common interface
Home-page: http://github.com/cuker/merchant-gateways/
Author: Cuker Interactive
Author-email: jasonk@cukerinteractive.com
License: MIT License
Keywords: django creditcard merchant authorization purchase
Platform: UNKNOWN
Classifier: Intended Audience :: Developers
Classifier: License :: OSI Approved :: MIT License
Classifier: Operating System :: OS Independent
Classifier: Programming Language :: Python
Classifier: Topic :: Software Development :: Testing
